pipedrive/__init__.py
pipedrive/activity.py
pipedrive/client.py
pipedrive/deal.py
pipedrive/deal_field.py
pipedrive/exceptions.py
pipedrive/person.py
pipedrive/person_field.py
pipedrive/util.py
pipedrive_wrapper-1.0.15.dist-info/LICENSE
pipedrive_wrapper-1.0.15.dist-info/METADATA
pipedrive_wrapper-1.0.15.dist-info/WHEEL
pipedrive_wrapper-1.0.15.dist-info/top_level.txt
pipedrive_wrapper-1.0.15.dist-info/RECORD
