Metadata-Version: 2.1
Name: pipedrive-wrapper
Version: 1.0.15
Summary: A Python wrapper for the Pipedrive API
Home-page: https://github.com/ppcantidio/pipedrive.py
Author: Pedro Cantidio
Author-email: ppcantidio@gmail.com
License: UNKNOWN
Platform: UNKNOWN
Classifier: Development Status :: 3 - Alpha
Classifier: Intended Audience :: Developers
Classifier: License :: OSI Approved :: MIT License
Classifier: Programming Language :: Python :: 3
License-File: LICENSE
